redblack/__init__.py
redblack/algorithms.py
redblack/containers.py
redblack-0.1.0.dist-info/LICENSE
redblack-0.1.0.dist-info/METADATA
redblack-0.1.0.dist-info/WHEEL
redblack-0.1.0.dist-info/top_level.txt
redblack-0.1.0.dist-info/RECORD
